spark_llm_eval/__init__.py
spark_llm_eval/agents/__init__.py
spark_llm_eval/agents/debate.py
spark_llm_eval/agents/tool_use.py
spark_llm_eval/agents/trajectory.py
spark_llm_eval/cache/__init__.py
spark_llm_eval/cache/config.py
spark_llm_eval/cache/delta_cache.py
spark_llm_eval/cache/key_generator.py
spark_llm_eval/cache/stats.py
spark_llm_eval/core/__init__.py
spark_llm_eval/core/config.py
spark_llm_eval/core/exceptions.py
spark_llm_eval/core/result.py
spark_llm_eval/core/task.py
spark_llm_eval/datasets/__init__.py
spark_llm_eval/datasets/delta_dataset.py
spark_llm_eval/evaluation/__init__.py
spark_llm_eval/evaluation/aggregator.py
spark_llm_eval/evaluation/base.py
spark_llm_eval/evaluation/lexical.py
spark_llm_eval/evaluation/llm_judge.py
spark_llm_eval/evaluation/rag.py
spark_llm_eval/evaluation/semantic.py
spark_llm_eval/inference/__init__.py
spark_llm_eval/inference/anthropic_engine.py
spark_llm_eval/inference/base.py
spark_llm_eval/inference/batch_udf.py
spark_llm_eval/inference/gemini_engine.py
spark_llm_eval/inference/openai_engine.py
spark_llm_eval/inference/rate_limiter.py
spark_llm_eval/orchestrator/__init__.py
spark_llm_eval/orchestrator/runner.py
spark_llm_eval/statistics/__init__.py
spark_llm_eval/statistics/confidence.py
spark_llm_eval/statistics/effect_size.py
spark_llm_eval/statistics/significance.py
spark_llm_eval/tracking/__init__.py
spark_llm_eval/tracking/mlflow_tracker.py
spark_llm_eval-0.1.3.dist-info/licenses/LICENSE
spark_llm_eval-0.1.3.dist-info/METADATA
spark_llm_eval-0.1.3.dist-info/WHEEL
spark_llm_eval-0.1.3.dist-info/top_level.txt
spark_llm_eval-0.1.3.dist-info/RECORD
