Metadata-Version: 2.4
Name: spark-llm-eval
Version: 0.1.3
Summary: Distributed LLM evaluation framework for Apache Spark
Author-email: Subhadip Mitra <contact@subhadipmitra.com>
Maintainer-email: Subhadip Mitra <contact@subhadipmitra.com>
License-Expression: Apache-2.0
Project-URL: Homepage, https://github.com/bassrehab/spark-llm-eval
Project-URL: Documentation, https://github.com/bassrehab/spark-llm-eval#readme
Project-URL: Repository, https://github.com/bassrehab/spark-llm-eval
Project-URL: Issues, https://github.com/bassrehab/spark-llm-eval/issues
Keywords: llm,evaluation,spark,pyspark,databricks,machine-learning,nlp,distributed-computing
Classifier: Development Status :: 3 - Alpha
Classifier: Intended Audience :: Developers
Classifier: Intended Audience :: Science/Research
Classifier: Operating System :: OS Independent
Classifier: Programming Language :: Python :: 3
Classifier: Programming Language :: Python :: 3.10
Classifier: Programming Language :: Python :: 3.11
Classifier: Programming Language :: Python :: 3.12
Classifier: Topic :: Scientific/Engineering :: Artificial Intelligence
Classifier: Topic :: Software Development :: Libraries :: Python Modules
Requires-Python: >=3.10
License-File: LICENSE
Requires-Dist: pyspark>=3.5.0
Requires-Dist: delta-spark>=3.0.0
Requires-Dist: mlflow>=2.10.0
Requires-Dist: pandas>=2.0.0
Requires-Dist: numpy>=1.24.0
Requires-Dist: scipy>=1.11.0
Requires-Dist: openai>=1.0.0
Requires-Dist: anthropic>=0.18.0
Requires-Dist: google-generativeai>=0.3.0
Requires-Dist: tiktoken>=0.5.0
Requires-Dist: jinja2>=3.1.0
Requires-Dist: rouge-score>=0.1.2
Requires-Dist: tenacity>=8.2.0
Provides-Extra: dev
Requires-Dist: pytest>=7.4.0; extra == "dev"
Requires-Dist: pytest-cov>=4.1.0; extra == "dev"
Requires-Dist: pytest-mock>=3.12.0; extra == "dev"
Requires-Dist: black>=23.0.0; extra == "dev"
Requires-Dist: ruff>=0.1.0; extra == "dev"
Requires-Dist: mypy>=1.5.0; extra == "dev"
Requires-Dist: pre-commit>=3.5.0; extra == "dev"
Provides-Extra: semantic
Requires-Dist: bert-score>=0.3.13; extra == "semantic"
Requires-Dist: sentence-transformers>=2.2.0; extra == "semantic"
Provides-Extra: all
Requires-Dist: spark-llm-eval[dev,semantic]; extra == "all"
Dynamic: license-file
